Metadata-Version: 2.1
Name: autouart
Version: 0.0.1
Summary: Automation UART
Author: Mani
License: UNKNOWN
Platform: UNKNOWN
